spunky.py
lib/__init__.py
lib/pygeoip.py
lib/pyquake3.py
lib/schedule.py
spunkybot-1.13.0.data/data/LICENSE
spunkybot-1.13.0.data/data/README.md
spunkybot-1.13.0.data/data/debian-startscript
spunkybot-1.13.0.data/data/systemd-spunkybot.service
spunkybot-1.13.0.data/data/lib/GeoIP.dat
spunkybot-1.13.0.dist-info/LICENSE
spunkybot-1.13.0.dist-info/METADATA
spunkybot-1.13.0.dist-info/WHEEL
spunkybot-1.13.0.dist-info/top_level.txt
spunkybot-1.13.0.dist-info/RECORD
