Metadata-Version: 2.1
Name: spunkybot
Version: 1.13.0
Summary: An automated game server bot and RCON tool for Urban Terror
Home-page: https://spunkybot.de/
Author: Alexander Kress
Author-email: feedback@spunkybot.de
License: MIT
Download-URL: https://github.com/SpunkyBot/spunkybot/releases/latest
Project-URL: Source Code, https://github.com/SpunkyBot/spunkybot
Project-URL: Documentation, https://docs.spunkybot.de
Project-URL: Bug Tracker, https://github.com/SpunkyBot/spunkybot/issues
Keywords: Urban Terror Game Administration RCON Bot
Platform: UNKNOWN
Classifier: Development Status :: 5 - Production/Stable
Classifier: Environment :: Console
Classifier: Intended Audience :: Developers
Classifier: Intended Audience :: System Administrators
Classifier: License :: OSI Approved :: MIT License
Classifier: Natural Language :: English
Classifier: Operating System :: OS Independent
Classifier: Programming Language :: Python :: 2.6
Classifier: Programming Language :: Python :: 2.7
Classifier: Topic :: System :: Logging
Classifier: Topic :: System :: Monitoring
Classifier: Topic :: System :: Systems Administration
Classifier: Topic :: Games/Entertainment
Classifier: Topic :: Utilities
Requires-Python: >=2.6
Requires-Dist: setuptools
